pyls_isort/__about__.py
pyls_isort/__init__.py
pyls_isort/plugin.py
pyls_isort-0.1.1.dist-info/DESCRIPTION.rst
pyls_isort-0.1.1.dist-info/METADATA
pyls_isort-0.1.1.dist-info/RECORD
pyls_isort-0.1.1.dist-info/WHEEL
pyls_isort-0.1.1.dist-info/entry_points.txt
pyls_isort-0.1.1.dist-info/metadata.json
pyls_isort-0.1.1.dist-info/top_level.txt
